config/MqttConfig.py
config/__init__.py
pyfrobot-0.1.17.dist-info/METADATA
pyfrobot-0.1.17.dist-info/WHEEL
pyfrobot-0.1.17.dist-info/top_level.txt
pyfrobot-0.1.17.dist-info/RECORD
