Metadata-Version: 2.1
Name: pyfrobot
Version: 0.1.17
Summary: Descripción de mi librería
Home-page: https://github.com/tu_usuario/mi_libreria
Author: alpeza
Author-email: alvaroperi.06@gmail.com
Classifier: License :: OSI Approved :: MIT License
Classifier: Programming Language :: Python :: 3
Classifier: Programming Language :: Python :: 3.6
Classifier: Programming Language :: Python :: 3.7
Classifier: Programming Language :: Python :: 3.8
Classifier: Programming Language :: Python :: 3.9
Requires-Dist: PyYAML (==6.0)
